{
  "$schema": "https://turborepo.dev/schema.json",
  "ui": "tui",
  "tasks": {
    "build": {
      "dependsOn": ["^build"],
      "inputs": ["$TURBO_DEFAULT$", ".env*"],
      "outputs": [".next/**", "!.next/cache/**", "!.next/dev/**"],
      "env": [
        "DATABASE_URL",
        "CLERK_SECRET_KEY",
        "CLERK_WEBHOOK_SECRET",
        "NEXT_PUBLIC_CLERK_PUBLISHABLE_KEY",
        "NEXT_PUBLIC_CLERK_SIGN_IN_URL",
        "NEXT_PUBLIC_CLERK_SIGN_UP_URL",
        "NEXT_PUBLIC_CLERK_AFTER_SIGN_IN_URL",
        "NEXT_PUBLIC_CLERK_AFTER_SIGN_UP_URL",
        "WHATSAPP_ACCESS_TOKEN",
        "WHATSAPP_PHONE_NUMBER_ID",
        "WHATSAPP_API_VERSION",
        "WHATSAPP_TEMPLATE_REMINDER_24H",
        "WHATSAPP_TEMPLATE_LANG",
        "CRON_SECRET",
        "APP_BASE_URL",
        "ADMIN_USER_IDS"
      ]
    },
    "lint": {
      "dependsOn": ["^lint"]
    },
    "check-types": {
      "dependsOn": ["^check-types"]
    },
    "dev": {
      "cache": false,
      "persistent": true
    }
  }
}